polyglot_hello/__init__.py
polyglot_hello/__main__.py
polyglot_hello/api.py
polyglot_hello/families.py
polyglot_hello/data/__init__.py
polyglot_hello/data/greetings.json
polyglot_hello-0.1.3.dist-info/METADATA
polyglot_hello-0.1.3.dist-info/WHEEL
polyglot_hello-0.1.3.dist-info/entry_points.txt
polyglot_hello-0.1.3.dist-info/licenses/LICENSE
polyglot_hello-0.1.3.dist-info/RECORD
