Metadata-Version: 2.4
Name: polyglot-hello
Version: 0.1.3
Summary: Hello and Hello World in 200+ languages, with simple APIs by name, code, or index.
Project-URL: Homepage, https://github.com/your-org/polyglot-hello
Project-URL: Repository, https://github.com/your-org/polyglot-hello
Project-URL: Issues, https://github.com/your-org/polyglot-hello/issues
Author: Polyglot Hello Maintainers
License:                                  Apache License
License-File: LICENSE
Keywords: greetings,hello,hello world,i18n,l10n,languages
Classifier: License :: OSI Approved :: Apache Software License
Classifier: Operating System :: OS Independent
Classifier: Programming Language :: Python
Classifier: Programming Language :: Python :: 3
Classifier: Programming Language :: Python :: 3 :: Only
Classifier: Programming Language :: Python :: 3.9
Classifier: Programming Language :: Python :: 3.10
Classifier: Programming Language :: Python :: 3.11
Classifier: Programming Language :: Python :: 3.12
Classifier: Programming Language :: Python :: 3.13
Classifier: Topic :: Software Development :: Internationalization
Classifier: Topic :: Text Processing :: Linguistic
Requires-Python: >=3.9
Provides-Extra: dev
Requires-Dist: mypy>=1.7; extra == 'dev'
Requires-Dist: pytest-cov>=4; extra == 'dev'
Requires-Dist: pytest>=7; extra == 'dev'
Requires-Dist: ruff>=0.5; extra == 'dev'
